new_year_2026/__init__.py
new_year_2026/cert.pem
new_year_2026/get_or_post.py
new_year_2026/key.pem
new_year_2026/mini_tls_server.py
new_year_2026/ssh_minimal_client.py
new_year_2026/tcp_client.py
new_year_2026/tcp_server.py
new_year_2026/tls_echo_client.py
new_year_2026/tls_echo_server.py
new_year_2026/examples/ctypes_shared/README.md
new_year_2026/examples/ctypes_shared/hello.c
new_year_2026/examples/ctypes_shared/hello_ctypes.py
new_year_2026/examples/ctypes_shared/libhello.so
new_year_2026/examples/extension_pkg/MANIFEST.in
new_year_2026/examples/extension_pkg/README.md
new_year_2026/examples/extension_pkg/pyproject.toml
new_year_2026/examples/extension_pkg/setup.py
new_year_2026/examples/extension_pkg/src/hello_ext/__init__.py
new_year_2026/examples/extension_pkg/src/hello_ext/bindings.cpp
new_year_2026/examples/extension_pkg/src/hello_ext/hello_c.c
new_year_2026/examples/extension_pkg/src/hello_ext/hello_c.h
new_year_2026/examples/extension_pkg/src/hello_ext/hello_cpp.cpp
new_year_2026/examples/extension_pkg/src/hello_ext/hello_cpp.h
2026_new_year-1.1.23.dist-info/METADATA
2026_new_year-1.1.23.dist-info/WHEEL
2026_new_year-1.1.23.dist-info/top_level.txt
2026_new_year-1.1.23.dist-info/RECORD
