Metadata-Version: 2.4
Name: 2026-new-year
Version: 1.1.23
Summary: TCP/TLS/HTTP/SSH learning scripts and demos.
Author-email: Tao Bo <taobo@example.com>
License: MIT
Requires-Python: >=3.9
